LICENSE
MANIFEST.in
README
setup.py
imposm/__init__.py
imposm.geocoder.egg-info/PKG-INFO
imposm.geocoder.egg-info/SOURCES.txt
imposm.geocoder.egg-info/dependency_links.txt
imposm.geocoder.egg-info/entry_points.txt
imposm.geocoder.egg-info/namespace_packages.txt
imposm.geocoder.egg-info/requires.txt
imposm.geocoder.egg-info/top_level.txt
imposm/geocoder/__init__.py
imposm/geocoder/app.py
imposm/geocoder/defaultmapping.py
imposm/geocoder/geocodemapping.py
imposm/geocoder/mapping.py
imposm/geocoder/config/__init__.py
imposm/geocoder/config/geocoder.ini
imposm/geocoder/db/__init__.py
imposm/geocoder/db/config.py
imposm/geocoder/db/line_merge.sql
imposm/geocoder/db/multiline_center.sql
imposm/geocoder/db/postgis.py
imposm/geocoder/model/__init__.py
imposm/geocoder/model/meta.py
imposm/geocoder/model/tables.py
imposm/geocoder/test/__init__.py
imposm/geocoder/test/test.osm
imposm/geocoder/test/test_imported.py
imposm/geocoder/test/test_lookup_field_type.py
imposm/geocoder/test/test_queries.py