Metadata-Version: 1.0
Name: imposm.geocoder
Version: 0.1.3
Summary: Imposm Geocoder for OSM-Data
Home-page: http://geocoder.imposm.org
Author: Marcel Radischat
Author-email: radischat@omniscale.de
License: Apache Software License 2.0
Platform: UNKNOWN
Classifier: Development Status :: 4 - Beta
Classifier: License :: OSI Approved :: Apache Software License
Classifier: Operating System :: OS Independent
Classifier: Programming Language :: Python :: 2.5
Classifier: Programming Language :: Python :: 2.6
Classifier: Programming Language :: Python :: 2.7
Classifier: Topic :: Scientific/Engineering :: GIS
